fat/__init__.py
fat/my_fat.py
my_factorial-0.0.1.dist-info/METADATA
my_factorial-0.0.1.dist-info/WHEEL
my_factorial-0.0.1.dist-info/top_level.txt
my_factorial-0.0.1.dist-info/RECORD
