Metadata-Version: 2.1
Name: my-factorial
Version: 0.0.1
Summary: calc the number factorial
Author: dadosneurais
Classifier: Programming Language :: Python :: 3
Classifier: License :: OSI Approved :: MIT License
Classifier: Operating System :: OS Independent
Requires-Python: >=3.6
